supervrpv3.py
supervrpv3-0.9.dist-info/LICENSE.txt
supervrpv3-0.9.dist-info/METADATA
supervrpv3-0.9.dist-info/WHEEL
supervrpv3-0.9.dist-info/top_level.txt
supervrpv3-0.9.dist-info/RECORD
