Metadata-Version: 2.1
Name: supervrpv3
Version: 0.9
Summary: mini super vrp v3
Author: smartlogAIlab
License: LICENSE.txt
Classifier: Programming Language :: Python :: 3.9
Classifier: License :: OSI Approved :: MIT License
License-File: LICENSE.txt
Requires-Dist: ortools
Requires-Dist: pyhumps
